agentkore/__init__.py
agentkore/kore.py
agentkore-0.1.0.dist-info/licenses/LICENSE
agentkore-0.1.0.dist-info/METADATA
agentkore-0.1.0.dist-info/WHEEL
agentkore-0.1.0.dist-info/top_level.txt
agentkore-0.1.0.dist-info/RECORD
