Metadata-Version: 2.4
Name: agentkore
Version: 0.1.0
Summary: A developer library for LLM-based agents
Author-email: David Lapsley <davidlapsleyio@gmail.com>
License: MIT License
Project-URL: Homepage, https://github.com/davidlapsleyio/agentkore
Project-URL: Repository, https://github.com/davidlapsleyio/agentkore.git
Requires-Python: >=3.8
License-File: LICENSE
Requires-Dist: openai>=0.27.0
Dynamic: license-file
